<Grammar>
    <VT>
        <symbol value = "1"/>
        <symbol value = "0"/>
  </VT>
  <VN>
      <symbol value = "A"/>
      <symbol value = "B"/>
      <symbol value = "B'"/>
      <symbol value = "C'"/>
      <symbol value = "C"/>
      <symbol value = "D"/>
  </VN>
  <StartSymbol value="A"/>
  <Matrix>
      <row>
          <symbol value = "B"/>
          <symbol value = "C'"/>
          <symbol value = ""/>
      </row>
      <row>
          <symbol value = ""/>
          <symbol value = "B'"/>
          <symbol value = ""/>
      </row>
      <row>
          <symbol value = ""/>
          <symbol value = "D"/>
          <symbol value = ""/>
      </row>
      <row>
          <symbol value = "C"/>
          <symbol value = ""/>
          <symbol value = ""/>
      </row>
      <row>
          <symbol value = "C"/>
          <symbol value = "'"/>
          <symbol value = "1"/>
      </row>
      <row>
          <symbol value = ""/>
          <symbol value = ""/>
          <symbol value = "1"/>
      </row>
  </Matrix>
</Grammar>